cloudframework/CoreFlask.py
cloudframework/RESTFul.py
cloudframework/__init__.py
cloudframework/api/__init__.py
cloudframework/api/_notfound.py
cloudframework/api/_version.py
cloudframework/lib/Buckets.py
cloudframework/lib/DataSQL.py
cloudframework/lib/DataStore.py
cloudframework/lib/Email.py
cloudframework/lib/__init__.py
cloudframework/python-dist/__init__.py
cloudframework/python-dist/install.py
cloudframework/python-dist/main.py
cloudframework/python-dist/api/__init__.py
cloudframework/python-dist/api/hello.py
cloudframework-1.0.16.dist-info/LICENSE
cloudframework-1.0.16.dist-info/METADATA
cloudframework-1.0.16.dist-info/WHEEL
cloudframework-1.0.16.dist-info/top_level.txt
cloudframework-1.0.16.dist-info/RECORD
