Metadata-Version: 2.1
Name: cloudframework
Version: 1.0.16
Summary: CloudFramework for Appengine using python language.
Home-page: https://github.com/CloudFramework-io/appengine-python-core-3.9
Author: CloudFramework Team
Author-email: tools@cloudframework.io
License: UNKNOWN
Platform: UNKNOWN
Classifier: Programming Language :: Python :: 3
Classifier: License :: OSI Approved :: MIT License
Classifier: Operating System :: OS Independent
Requires-Dist: Flask ==3.0.0
Requires-Dist: psutil
